caspercm/__init__.py
caspercm/jupyter_caspercm.py
caspercm-0.0.3.dist-info/LICENSE
caspercm-0.0.3.dist-info/METADATA
caspercm-0.0.3.dist-info/WHEEL
caspercm-0.0.3.dist-info/top_level.txt
caspercm-0.0.3.dist-info/RECORD
