Metadata-Version: 2.1
Name: caspercm
Version: 0.0.3
Summary: JupyterLab Content Manager Using Oracle Cloud Object Store
Home-page: https://github.com/stonezhong/caspercm
Author: Stone Zhong
Author-email: stonezhong@hotmail.com
License: MIT
Platform: UNKNOWN
Classifier: License :: OSI Approved :: MIT License
Classifier: Programming Language :: Python :: 3
Requires-Dist: oci
